mangadex_downloader/__init__.py
mangadex_downloader/__main__.py
mangadex_downloader/artist_and_author.py
mangadex_downloader/chapter.py
mangadex_downloader/cover.py
mangadex_downloader/downloader.py
mangadex_downloader/errors.py
mangadex_downloader/fetcher.py
mangadex_downloader/filters.py
mangadex_downloader/forums.py
mangadex_downloader/group.py
mangadex_downloader/iterator.py
mangadex_downloader/json_op.py
mangadex_downloader/language.py
mangadex_downloader/main.py
mangadex_downloader/manga.py
mangadex_downloader/mdlist.py
mangadex_downloader/network.py
mangadex_downloader/progress_bar.py
mangadex_downloader/range.py
mangadex_downloader/tag.py
mangadex_downloader/update.py
mangadex_downloader/user.py
mangadex_downloader/utils.py
mangadex_downloader/auth/__init__.py
mangadex_downloader/auth/base.py
mangadex_downloader/auth/legacy.py
mangadex_downloader/auth/oauth2.py
mangadex_downloader/cli/__init__.py
mangadex_downloader/cli/args_parser.py
mangadex_downloader/cli/auth.py
mangadex_downloader/cli/command.py
mangadex_downloader/cli/config.py
mangadex_downloader/cli/download.py
mangadex_downloader/cli/update.py
mangadex_downloader/cli/url.py
mangadex_downloader/cli/utils.py
mangadex_downloader/config/__init__.py
mangadex_downloader/config/auth_cache.py
mangadex_downloader/config/config.py
mangadex_downloader/config/env.py
mangadex_downloader/config/utils.py
mangadex_downloader/fonts/GNU FreeFont/AUTHORS
mangadex_downloader/fonts/GNU FreeFont/COPYING
mangadex_downloader/fonts/GNU FreeFont/CREDITS
mangadex_downloader/fonts/GNU FreeFont/README
mangadex_downloader/fonts/GNU FreeFont/otf/FreeSans.otf
mangadex_downloader/fonts/GNU FreeFont/otf/FreeSansBold.otf
mangadex_downloader/fonts/GNU FreeFont/otf/FreeSansBoldOblique.otf
mangadex_downloader/fonts/GNU FreeFont/otf/FreeSansOblique.otf
mangadex_downloader/fonts/GNU FreeFont/ttf/FreeSans.ttf
mangadex_downloader/fonts/GNU FreeFont/ttf/FreeSansBold.ttf
mangadex_downloader/fonts/GNU FreeFont/ttf/FreeSansBoldOblique.ttf
mangadex_downloader-3.1.4.dist-info/licenses/LICENSE
mangadex_downloader-3.1.4.dist-info/METADATA
mangadex_downloader-3.1.4.dist-info/WHEEL
mangadex_downloader-3.1.4.dist-info/entry_points.txt
mangadex_downloader-3.1.4.dist-info/top_level.txt
mangadex_downloader-3.1.4.dist-info/RECORD
