Metadata-Version: 2.4
Name: mangadex-downloader
Version: 3.1.4
Summary: A Command-line tool to download manga from MangaDex, written in Python
Home-page: https://github.com/mansuf/mangadex-downloader
Download-URL: https://github.com/mansuf/mangadex-downloader/releases
Author: Rahman Yusuf
Author-email: danipart4@gmail.com
License: MIT
Keywords: mangadex
Classifier: Development Status :: 5 - Production/Stable
Classifier: Intended Audience :: End Users/Desktop
Classifier: License :: OSI Approved :: MIT License
Classifier: Programming Language :: Python :: 3 :: Only
Classifier: Programming Language :: Python :: 3
Classifier: Programming Language :: Python :: 3.10
Classifier: Programming Language :: Python :: 3.11
Classifier: Programming Language :: Python :: 3.12
Classifier: Programming Language :: Python :: 3.13
Requires-Python: >=3.10
License-File: LICENSE
Requires-Dist: requests-doh==1.0.0
Requires-Dist: requests[socks]
Requires-Dist: tqdm
Requires-Dist: pathvalidate
Requires-Dist: packaging
Requires-Dist: pyjwt
Requires-Dist: beautifulsoup4
Requires-Dist: Pillow==11.1.0
Requires-Dist: chardet
Provides-Extra: docs
Requires-Dist: furo; extra == "docs"
Requires-Dist: myst-parser[linkify]; extra == "docs"
Provides-Extra: optional
Requires-Dist: py7zr==0.22.0; extra == "optional"
Requires-Dist: orjson==3.10.15; extra == "optional"
Requires-Dist: lxml==5.3.0; extra == "optional"
Requires-Dist: Authlib; extra == "optional"
Dynamic: author
Dynamic: author-email
Dynamic: classifier
Dynamic: description
Dynamic: description-content-type
Dynamic: download-url
Dynamic: home-page
Dynamic: keywords
Dynamic: license
Dynamic: license-file
Dynamic: provides-extra
Dynamic: requires-dist
Dynamic: requires-python
Dynamic: summary
